README.md
setup.py
oren_v1_pack/__init__.py
oren_v1_pack/adder.py
oren_v1_pack/adder_prin.py
oren_v1_pack.egg-info/PKG-INFO
oren_v1_pack.egg-info/SOURCES.txt
oren_v1_pack.egg-info/dependency_links.txt
oren_v1_pack.egg-info/not-zip-safe
oren_v1_pack.egg-info/top_level.txt