Metadata-Version: 1.0
Name: oren-v1-pack
Version: 0.1
Summary: oren_first_pack
Home-page: UNKNOWN
Author: UNKNOWN
Author-email: UNKNOWN
License: UNKNOWN
Platform: UNKNOWN
